python_coach/__about__.py
python_coach/__init__.py
python_coach/dev_runner.py
python_coach/entry_points.py
python_coach/python_coach.py
python_coach/code_runner/result_case.py
python_coach/code_runner/runner.py
python_coach/datacontext/data_json.json
python_coach/datacontext/dc.py
python_coach/datacontext/quiz_content.py
python_coach/ui/app.tcss
python_coach/ui/runner_app.py
python_coach/ui/auth_screen/auth.py
python_coach/ui/auth_screen/auth.tcss
python_coach/ui/editor_screen/editor.py
python_coach/ui/editor_screen/editor.tcss
python_coach/ui/editor_screen/actions/editor_actions.py
python_coach/ui/editor_screen/actions/init_action.py
python_coach/ui/editor_screen/components/code_editor.py
python_coach/ui/editor_screen/components/current_task.py
python_coach/ui/editor_screen/components/explorer.py
python_coach/ui/editor_screen/components/quiz_description.py
python_coach/ui/editor_screen/components/test_results.py
python_coach/ui/file_screen/open_file_screen.py
python_coach/ui/file_screen/open_file_screen.tcss
python_coach/ui/state/app_reducer.py
python_coach/ui/state/app_state.py
python_coach/ui/state/base_action.py
python_coach/ui/state/selectors.py
python_coach-1.0.8.dist-info/METADATA
python_coach-1.0.8.dist-info/WHEEL
python_coach-1.0.8.dist-info/entry_points.txt
python_coach-1.0.8.dist-info/licenses/LICENSE.txt
python_coach-1.0.8.dist-info/RECORD
