Metadata-Version: 2.4
Name: python-coach
Version: 1.0.8
Project-URL: Documentation, https://github.com/U.N. Owen/python-coach#readme
Project-URL: Issues, https://github.com/U.N. Owen/python-coach/issues
Project-URL: Source, https://github.com/U.N. Owen/python-coach
Author-email: Analyst Klondike <analyst-klondike@yandex.ru>
License: Commercial License
License-File: LICENSE.txt
Classifier: Development Status :: 4 - Beta
Classifier: Programming Language :: Python
Classifier: Programming Language :: Python :: 3.8
Classifier: Programming Language :: Python :: 3.9
Classifier: Programming Language :: Python :: 3.10
Classifier: Programming Language :: Python :: 3.11
Classifier: Programming Language :: Python :: 3.12
Classifier: Programming Language :: Python :: Implementation :: CPython
Classifier: Programming Language :: Python :: Implementation :: PyPy
Requires-Python: >=3.8
Requires-Dist: textual==3.2.0
Requires-Dist: textual[syntax]
